pictokit/__about__.py
pictokit/__init__.py
pictokit/common.py
pictokit/constants.py
pictokit/controls.py
pictokit/element_wise.py
pictokit/utils.py
pictokit-0.3.0.dist-info/METADATA
pictokit-0.3.0.dist-info/WHEEL
pictokit-0.3.0.dist-info/RECORD
