Metadata-Version: 2.1
Name: pictokit
Version: 0.3.0
Summary: Uma lib python que oferece uma serie de ferramentas para o processamento de imagem
Author: Fabio Oliveira
Author-email: fabio.oliveira1403@outlook.com
Requires-Python: >=3.10,<4.0
Classifier: Programming Language :: Python :: 3
Classifier: Programming Language :: Python :: 3.10
Classifier: Programming Language :: Python :: 3.11
Classifier: Programming Language :: Python :: 3.12
Requires-Dist: beartype (>=0.21.0,<0.22.0)
Requires-Dist: matplotlib (>=3.8,<4.0)
Requires-Dist: numpy (>=2.0,<3.0)
Requires-Dist: opencv-python (>=4.9,<5.0)
Requires-Dist: pandas (>=2.3.2)
Requires-Dist: python-dotenv (>=1.1.1,<2.0.0)
Project-URL: repository, https://github.com/fabrik5k/pictokit
